README.txt
TODO.txt
setup.cfg
setup.py
collective/__init__.py
collective.habla.egg-info/PKG-INFO
collective.habla.egg-info/SOURCES.txt
collective.habla.egg-info/dependency_links.txt
collective.habla.egg-info/entry_points.txt
collective.habla.egg-info/namespace_packages.txt
collective.habla.egg-info/not-zip-safe
collective.habla.egg-info/requires.txt
collective.habla.egg-info/top_level.txt
collective/habla/README.txt
collective/habla/__init__.py
collective/habla/browser.py
collective/habla/configure.zcml
collective/habla/disable_chat.png
collective/habla/enable_chat.png
collective/habla/habla_portlets.pt
collective/habla/interfaces.py
collective/habla/tests.py
collective/habla/viewlets.py
collective/habla/locales/collective.habla.pot
collective/habla/locales/rebuild.sh
collective/habla/locales/it/LC_MESSAGES/collective.habla.mo
collective/habla/locales/it/LC_MESSAGES/collective.habla.po
collective/habla/profiles/default/actionicons.xml
collective/habla/profiles/default/actions.xml
collective/habla/profiles/default/browserlayer.xml
collective/habla/profiles/default/metadata.xml
collective/habla/profiles/default/registry.xml
collective/habla/profiles/default/viewlets.xml
docs/HISTORY.txt
docs/INSTALL.txt
docs/LICENSE.GPL
docs/LICENSE.txt