Metadata-Version: 1.0
Name: collective.habla
Version: 0.3
Summary: Hab.la web chat for Plone
Home-page: https://svn.plone.org/svn/collective/collective.habla
Author: Giorgio Borelli
Author-email: giorgio@giorgioborelli.it
License: GPL
Keywords: Plone chat hab.la
Platform: UNKNOWN
Classifier: Framework :: Plone
Classifier: Programming Language :: Python
Classifier: Topic :: Software Development :: Libraries :: Python Modules
